README
setup.py
bambu_api/__init__.py
bambu_api/admin.py
bambu_api/apps.py
bambu_api/decorators.py
bambu_api/endpoints.py
bambu_api/exceptions.py
bambu_api/forms.py
bambu_api/helpers.py
bambu_api/managers.py
bambu_api/menus.py
bambu_api/models.py
bambu_api/options.py
bambu_api/requestlogging.py
bambu_api/requests.py
bambu_api/response.py
bambu_api/serialisers.py
bambu_api/sites.py
bambu_api/test_endpoints.py
bambu_api/transformers.py
bambu_api/urls.py
bambu_api.egg-info/PKG-INFO
bambu_api.egg-info/SOURCES.txt
bambu_api.egg-info/dependency_links.txt
bambu_api.egg-info/requires.txt
bambu_api.egg-info/top_level.txt
bambu_api/auth/__init__.py
bambu_api/auth/decorators.py
bambu_api/auth/http.py
bambu_api/auth/oauth2.py
bambu_api/auth/session.py
bambu_api/migrations/0001_initial.py
bambu_api/migrations/__init__.py
bambu_api/templates/api/401.html
bambu_api/templates/api/base.html
bambu_api/templates/api/apps/delete.html
bambu_api/templates/api/apps/edit.html
bambu_api/templates/api/apps/list.html
bambu_api/templates/api/auth/oauth/authorise.html
bambu_api/templates/api/doc/app_index.html
bambu_api/templates/api/doc/base.html
bambu_api/templates/api/doc/endpoints.inc.html
bambu_api/templates/api/doc/index.html
bambu_api/templates/api/doc/model.html
bambu_api/templatetags/__init__.py
bambu_api/templatetags/prettycode.py
bambu_api/xml/__init__.py