Metadata-Version: 1.1
Name: bambu-api
Version: 2.0.1
Summary: Quickly expose your models to a JSON or XML API, authenticated via HTTP or OAuth.
Home-page: https://github.com/iamsteadman/bambu-api
Author: Steadman
Author-email: mark@steadman.io
License: UNKNOWN
Platform: UNKNOWN
Classifier: Development Status :: 4 - Beta
Classifier: Environment :: Web Environment
Classifier: Framework :: Django
